gnor/__init__.py
gnor/py.typed
gnor/settings.py
gnor/cli/__init__.py
gnor/cli/cli.py
gnor/src/__init__.py
gnor/src/github_stacks.py
gnor/src/gitignore.py
gnor/src/signature.py
gnor/src/utils.py
gnor-0.0.2.dist-info/METADATA
gnor-0.0.2.dist-info/WHEEL
gnor-0.0.2.dist-info/entry_points.txt
gnor-0.0.2.dist-info/RECORD
