Metadata-Version: 2.4
Name: gnor
Version: 0.0.2
Summary: A command line tool to generate a .gitignore file
Project-URL: Homepage, https://github.com/machadoah/gnor
Project-URL: Documentation, https://github.com/machadoah/gnor
Project-URL: Repository, https://github.com/machadoah/gnor
Project-URL: Issues, https://github.com/machadoah/gnor/issues
Project-URL: Changelog, https://github.com/machadoah/gnor/releases
Author-email: Antonio Henrique Machado <machadoah@proton.me>
Classifier: License :: OSI Approved :: MIT License
Classifier: Programming Language :: Python :: 3 :: Only
Classifier: Programming Language :: Python :: 3.10
Classifier: Programming Language :: Python :: 3.11
Classifier: Programming Language :: Python :: 3.12
Classifier: Typing :: Typed
Requires-Python: >=3.10
Requires-Dist: pydantic-settings>=2.9.1
Requires-Dist: pydantic>=2.11.5
Requires-Dist: requests>=2.32.3
Requires-Dist: typer>=0.15.4
